py_bench/__init__.py
py_bench/_dynamic_benchmark.py
py_bench/_version.py
py_bench/bench_runner.py
py_bench/benchmark_call_result_visualizer.py
py_bench/benchmark_executor.py
py_bench/common.py
py_bench/loader.py
py_bench/math_utils.py
py_bench/result_comparer.py
py_bench/utils.py
py_bench/bench_registry/__init__.py
py_bench/bench_registry/bench_regisrty.py
py_bench/bench_registry/decorators.py
py_bench/result_visualizer/__init__.py
py_bench/result_visualizer/common.py
py_bench/result_visualizer/result_formatter.py
py_bench/result_visualizer/result_printer.py
py_bench-0.1.0.dev3.dist-info/LICENSE
py_bench-0.1.0.dev3.dist-info/METADATA
py_bench-0.1.0.dev3.dist-info/WHEEL
py_bench-0.1.0.dev3.dist-info/top_level.txt
py_bench-0.1.0.dev3.dist-info/RECORD
