Metadata-Version: 2.1
Name: py_bench
Version: 0.1.0.dev3
Summary: py_bench: python benchmark tool
Author: 1MrEnot
License: MIT License
License-File: LICENSE
